kswutils_matplot/__init__.py
kswutils_matplot/matplot_fig.py
kswutils_matplot-0.0.2.dist-info/METADATA
kswutils_matplot-0.0.2.dist-info/WHEEL
kswutils_matplot-0.0.2.dist-info/licenses/LICENSE
kswutils_matplot-0.0.2.dist-info/RECORD
