Metadata-Version: 2.3
Name: kswutils_matplot
Version: 0.0.2
Summary: Plotly Graph
Author-email: Justin <shuwa108@gmail.com>
License-File: LICENSE
Classifier: License :: OSI Approved :: MIT License
Classifier: Operating System :: OS Independent
Classifier: Programming Language :: Python :: 3
Requires-Python: >=3.8
